odoo10_addon_l10n_taiwan-10.0.1.0.0.99.dev5-py2.7-nspkg.pth
odoo/addons/l10n_taiwan/README.rst
odoo/addons/l10n_taiwan/__init__.py
odoo/addons/l10n_taiwan/__manifest__.py
odoo/addons/l10n_taiwan/data/data_taiwan.xml
odoo/addons/l10n_taiwan/static/description/icon.png
odoo10_addon_l10n_taiwan-10.0.1.0.0.99.dev5.dist-info/METADATA
odoo10_addon_l10n_taiwan-10.0.1.0.0.99.dev5.dist-info/RECORD
odoo10_addon_l10n_taiwan-10.0.1.0.0.99.dev5.dist-info/WHEEL
odoo10_addon_l10n_taiwan-10.0.1.0.0.99.dev5.dist-info/namespace_packages.txt
odoo10_addon_l10n_taiwan-10.0.1.0.0.99.dev5.dist-info/top_level.txt
