Metadata-Version: 2.1
Name: odoo10-addon-l10n-taiwan
Version: 10.0.1.0.0.99.dev5
Summary: This module adds state data for Taiwan Localization.
Home-page: https://www.elico-corp.com
Author: Elico Corp, Odoo Community Association (OCA)
Author-email: support@odoo-community.org
License: UNKNOWN
Platform: UNKNOWN
Classifier: Programming Language :: Python
Classifier: Framework :: Odoo
Requires-Python: ~=2.7
Requires-Dist: odoo (<10.1dev,>=10.0)
